deconvolute/__init__.py
deconvolute/constants.py
deconvolute/errors.py
deconvolute/clients/__init__.py
deconvolute/clients/base.py
deconvolute/clients/openai.py
deconvolute/core/__init__.py
deconvolute/core/defaults.py
deconvolute/core/orchestrator.py
deconvolute/detectors/__init__.py
deconvolute/detectors/base.py
deconvolute/detectors/content/__init__.py
deconvolute/detectors/content/language/__init__.py
deconvolute/detectors/content/language/engine.py
deconvolute/detectors/content/language/models.py
deconvolute/detectors/content/signature/__init__.py
deconvolute/detectors/content/signature/engine.py
deconvolute/detectors/content/signature/rules/base.yar
deconvolute/detectors/integrity/__init__.py
deconvolute/detectors/integrity/canary/__init__.py
deconvolute/detectors/integrity/canary/engine.py
deconvolute/detectors/integrity/canary/generator.py
deconvolute/detectors/integrity/canary/models.py
deconvolute/utils/logger.py
deconvolute-0.1.0a9.dist-info/METADATA
deconvolute-0.1.0a9.dist-info/WHEEL
deconvolute-0.1.0a9.dist-info/licenses/LICENSE
deconvolute-0.1.0a9.dist-info/RECORD
