Metadata-Version: 2.4
Name: deconvolute
Version: 0.1.0a9
Summary: Deconvolute is a defense-in-depth SDK designed to secure every stage of your Retrieval Augmented Generation (RAG) pipeline.
Project-URL: Homepage, https://deconvoluteai.com
Project-URL: Issues, https://github.com/daved01/deconvolute/issues
Author-email: David Kirchhoff <david@deconvoluteai.com>
License-Expression: Apache-2.0
License-File: LICENSE
Classifier: Development Status :: 3 - Alpha
Classifier: Intended Audience :: Developers
Classifier: License :: OSI Approved :: Apache Software License
Classifier: Programming Language :: Python :: 3.11
Classifier: Programming Language :: Python :: 3.12
Classifier: Programming Language :: Python :: 3.13
Classifier: Topic :: Security
Classifier: Topic :: Software Development :: Libraries :: Python Modules
Classifier: Topic :: Software Development :: Quality Assurance
Requires-Python: >=3.11
Requires-Dist: lingua-language-detector>=2.1.1
Requires-Dist: pydantic-settings>=2.0
Requires-Dist: pydantic>=2.0
Requires-Dist: yara-python>=4.5.4
